eodms_api_client/__init__.py
eodms_api_client/auth.py
eodms_api_client/cli.py
eodms_api_client/eodms.py
eodms_api_client/geo.py
eodms_api_client/params.py
eodms_api_client-1.3.1.dist-info/licenses/LICENSE
eodms_api_client-1.3.1.dist-info/METADATA
eodms_api_client-1.3.1.dist-info/WHEEL
eodms_api_client-1.3.1.dist-info/entry_points.txt
eodms_api_client-1.3.1.dist-info/top_level.txt
eodms_api_client-1.3.1.dist-info/RECORD
