Metadata-Version: 2.4
Name: eodms_api_client
Version: 1.3.1
Summary: Tool for querying and submitting image orders to Natural Resources Canada's Earth Observation Data Management System (EODMS)
Home-page: https://eodms-api-client.readthedocs.io/en/latest
Author: Mike Brady
Author-email: mike.brady@canada.ca
License: MIT
Project-URL: Source, https://github.com/m9brady/eodms-api-client
Project-URL: Tracker, https://github.com/m9brady/eodms-api-client/issues
Classifier: Programming Language :: Python :: 3
Classifier: License :: OSI Approved :: MIT License
Classifier: Operating System :: OS Independent
Requires-Python: ~=3.6
License-File: LICENSE
Requires-Dist: requests
Requires-Dist: click
Requires-Dist: python-dateutil
Requires-Dist: tqdm
Requires-Dist: pandas>=1.0.0
Requires-Dist: geopandas>=0.8
Requires-Dist: pyproj
Requires-Dist: fiona
Provides-Extra: dev
Requires-Dist: pytest; extra == "dev"
Requires-Dist: requests-mock; extra == "dev"
Requires-Dist: rstcheck; extra == "dev"
Dynamic: author
Dynamic: author-email
Dynamic: classifier
Dynamic: description
Dynamic: description-content-type
Dynamic: home-page
Dynamic: license
Dynamic: license-file
Dynamic: project-url
Dynamic: provides-extra
Dynamic: requires-dist
Dynamic: requires-python
Dynamic: summary
